omxware/OmxResponse.py
omxware/__init__.py
omxware/omxware.py
omxware/omxwaredev.py
omxware/config/Configuration.py
omxware/config/Connection.py
omxware/config/OmxConfig.py
omxware/config/__init__.py
omxware/config/omxware.cfg
omxware/entities/Domain.py
omxware/entities/Entity.py
omxware/entities/Gene.py
omxware/entities/Genome.py
omxware/entities/Genus.py
omxware/entities/GoTerm.py
omxware/entities/IprCode.py
omxware/entities/Protein.py
omxware/entities/User.py
omxware/entities/__init__.py
omxware/exceptions/DataException.py
omxware/exceptions/Error.py
omxware/exceptions/InvalidParamsException.py
omxware/exceptions/ServiceException.py
omxware/exceptions/__init__.py
omxware/utils/AESCipher.py
omxware/utils/ApiUtils.py
omxware/utils/ResultUtils.py
omxware/utils/SecUtils.py
omxware/utils/__init__.py
omxware-0.1.50.dist-info/AUTHORS.rst
omxware-0.1.50.dist-info/METADATA
omxware-0.1.50.dist-info/WHEEL
omxware-0.1.50.dist-info/top_level.txt
omxware-0.1.50.dist-info/RECORD
