Metadata-Version: 2.1
Name: omxware
Version: 0.1.50
Summary: IBM Functional Genomics Platform SDK to explore data.
Home-page: https://github.ibm.com/GrandChallenge-Almaden/omxware-pypi
Author: Harsha Krishnareddy
Author-email: hvkrishn@us.ibm.com
License: IBM
Keywords: omxware,IBM Functional Genomics Platform
Platform: UNKNOWN
Classifier: Development Status :: 2 - Pre-Alpha
Classifier: Intended Audience :: Developers
Classifier: Natural Language :: English
Classifier: Programming Language :: Python :: 3
Classifier: Programming Language :: Python :: 3.5
Classifier: Programming Language :: Python :: 3.6
Classifier: Programming Language :: Python :: 3.7
Requires-Dist: python-keycloak (==0.22.0)
Requires-Dist: simplejson (>=3.16.0)
Requires-Dist: pandas
Requires-Dist: configparser
Requires-Dist: requests
Requires-Dist: urllib3 (<=1.24.2)
Requires-Dist: IPython
Requires-Dist: matplotlib
Requires-Dist: pycryptodome
